{
    "groupId": "restore",
    "locale": "uk-ua",
    "schema": "localeStrings",
    "strings": {
        "weResolvedIt": "Виникла проблема, але ми її вже вирішили",
        "clearedData": "Оскільки із запуском Microsoft Edge виникла проблема, нам довелось очистити деякі дані, щоб ви знову могли переглядати веб-сайти.",
        "favoritesOK": "Уподобання та паролі – на місці",
        "favoritesSaved": "Ми зберегли їх для вас без жодних змін.",
        "historyAndCookies": "Історія та файли cookie",
        "signBackIn": "Ці дані було очищено, тож, відкриваючи веб-сайти, потрібно буде знову ввести дані для входу.",
        "settingsExtensions": "Параметри й розширення",
        "changedSettings": "Якщо ви вносили зміни в якісь параметри чи розширення, ці дії потрібно буде повторити."
    }
}
