{
    "speedWelcomeToEdge": "Microsoft Edge へようこそ",
    "speedWelcomeWindows10": "Windows 10 のために設計された、軽快で安全なブラウザー",
    "speedFaster": "安心してネットを利用できる安全なブラウザー",
    "speedGooglesBenchmark": "",
    "speedMicrosoftEdge": "Microsoft Edge <br>",
    "speedFastest": "最速",
    "speedScore": "スピード スコア",
    "speedChrome": "Google Chrome",
    "speedChromeSlower": "<strong>&mdash;</strong> 5% 低速",
    "speedFirefox": "Mozilla Firefox",
    "speedFirefoxSlower": "<strong>&mdash;</strong> 9% 低速",    
    "speedGetStarted": "今すぐ使ってみる",
    "importBookmarks": "お気に入りをインポートする ",
    "customizeWithExtensions": "拡張機能でカスタマイズする ",
    "seeWhatsNew": "Web ページに書き込む "
}